[
{
  "pk": 1, 
  "model": "apps.application", 
  "fields": {
    "category": 1, 
    "pingdom_id": 953981, 
    "title": "Greg's Dropbox"
  }
},
{
  "pk": 2, 
  "model": "apps.application", 
  "fields": {
    "category": 1, 
    "pingdom_id": 953983, 
    "title": "Asana App Login"
  }
},
{
  "pk": 3, 
  "model": "apps.application", 
  "fields": {
    "category": 1, 
    "pingdom_id": 953985, 
    "title": "Chartio Login"
  }
},
{
  "pk": 4, 
  "model": "apps.application", 
  "fields": {
    "category": 1, 
    "pingdom_id": 953987, 
    "title": "Zen Desk random account"
  }
}
]
